README.md
setup.py
django_pgqueue.egg-info/PKG-INFO
django_pgqueue.egg-info/SOURCES.txt
django_pgqueue.egg-info/dependency_links.txt
django_pgqueue.egg-info/top_level.txt
pgqueue/__init__.py
pgqueue/admin.py
pgqueue/decorators.py
pgqueue/models.py
pgqueue/queue.py
pgqueue/tests.py
pgqueue/utils.py
pgqueue/worker.py
pgqueue/migrations/0001_initial.py
pgqueue/migrations/0002_job_context.py
pgqueue/migrations/0003_auto_20181104_2213.py
pgqueue/migrations/__init__.py