Metadata-Version: 1.1
Name: django-pgqueue
Version: 0.9.2
Summary: PostgreSQL-based task queue for Django
Home-page: https://github.com/zenwalker/django-pgqueue
Author: Max Poletaev
Author-email: max.poletaev@gmail.com
License: BSD
Keywords: django postgres queue
Platform: UNKNOWN
Classifier: Development Status :: 4 - Beta
Classifier: Programming Language :: Python
Classifier: Programming Language :: Python :: 3.5
Classifier: Programming Language :: Python :: 3.6
Classifier: Programming Language :: Python :: 3.7
Classifier: Framework :: Django
Classifier: Framework :: Django :: 2.0
Classifier: Framework :: Django :: 2.1
Classifier: Framework :: Django :: 2.2
